infobeamerhosted/API.py
infobeamerhosted/Exceptions.py
infobeamerhosted/Infobeamer.py
infobeamerhosted/__init__.py
infobeamerhosted/__main__.py
infobeamerhosted-1.0.dist-info/LICENSE
infobeamerhosted-1.0.dist-info/METADATA
infobeamerhosted-1.0.dist-info/WHEEL
infobeamerhosted-1.0.dist-info/top_level.txt
infobeamerhosted-1.0.dist-info/RECORD
