Metadata-Version: 2.1
Name: infobeamerhosted
Version: 1.0
Summary: Python wrapper around the Info Beamer Hosted API.
Home-page: https://github.com/zkmkarlsruhe/pypi-infobeamerhosted
Author: Christian Lölkes
Author-email: christian.loelkes@gmail.com
License: UNKNOWN
Platform: UNKNOWN
Classifier: Programming Language :: Python :: 3
Classifier: License :: OSI Approved :: MIT License
Classifier: Operating System :: OS Independent
Requires-Python: >=3.5
Requires-Dist: requests
